{
  "name": "Brazil/West",
  "table": [
    [ "-62167168800", { "is_dst": false, "offset": -14400 } ],
    [ "-1767211196", { "is_dst": false, "offset": -14400 } ],
    [ "-1206954000", { "is_dst": true, "offset": -10800 } ],
    [ "-1191358800", { "is_dst": false, "offset": -14400 } ],
    [ "-1175371200", { "is_dst": true, "offset": -10800 } ],
    [ "-1159822800", { "is_dst": false, "offset": -14400 } ],
    [ "-633816000", { "is_dst": true, "offset": -10800 } ],
    [ "-622065600", { "is_dst": false, "offset": -14400 } ],
    [ "-602280000", { "is_dst": true, "offset": -10800 } ],
    [ "-591829200", { "is_dst": false, "offset": -14400 } ],
    [ "-570744000", { "is_dst": true, "offset": -10800 } ],
    [ "-560206800", { "is_dst": false, "offset": -14400 } ],
    [ "-539121600", { "is_dst": true, "offset": -10800 } ],
    [ "-531349200", { "is_dst": false, "offset": -14400 } ],
    [ "-191361600", { "is_dst": true, "offset": -10800 } ],
    [ "-184194000", { "is_dst": false, "offset": -14400 } ],
    [ "-155160000", { "is_dst": true, "offset": -10800 } ],
    [ "-150066000", { "is_dst": false, "offset": -14400 } ],
    [ "-128894400", { "is_dst": true, "offset": -10800 } ],
    [ "-121122000", { "is_dst": false, "offset": -14400 } ],
    [ "-99950400", { "is_dst": true, "offset": -10800 } ],
    [ "-89586000", { "is_dst": false, "offset": -14400 } ],
    [ "-68414400", { "is_dst": true, "offset": -10800 } ],
    [ "-57963600", { "is_dst": false, "offset": -14400 } ],
    [ "499752000", { "is_dst": true, "offset": -10800 } ],
    [ "511239600", { "is_dst": false, "offset": -14400 } ],
    [ "530596800", { "is_dst": true, "offset": -10800 } ],
    [ "540270000", { "is_dst": false, "offset": -14400 } ],
    [ "562132800", { "is_dst": true, "offset": -10800 } ],
    [ "571201200", { "is_dst": false, "offset": -14400 } ],
    [ "750830400", { "is_dst": true, "offset": -10800 } ],
    [ "761713200", { "is_dst": false, "offset": -14400 } ]
  ]
}