{
  "name": "Africa/Casablanca",
  "table": [
    [ "-62167168800", { "is_dst": false, "offset": 0 } ],
    [ "-1773012580", { "is_dst": false, "offset": 0 } ],
    [ "-956361600", { "is_dst": true, "offset": 3600 } ],
    [ "-950490000", { "is_dst": false, "offset": 0 } ],
    [ "-942019200", { "is_dst": true, "offset": 3600 } ],
    [ "-761187600", { "is_dst": false, "offset": 0 } ],
    [ "-617241600", { "is_dst": true, "offset": 3600 } ],
    [ "-605149200", { "is_dst": false, "offset": 0 } ],
    [ "-81432000", { "is_dst": true, "offset": 3600 } ],
    [ "-71110800", { "is_dst": false, "offset": 0 } ],
    [ "141264000", { "is_dst": true, "offset": 3600 } ],
    [ "147222000", { "is_dst": false, "offset": 0 } ],
    [ "199756800", { "is_dst": true, "offset": 3600 } ],
    [ "207702000", { "is_dst": false, "offset": 0 } ],
    [ "231292800", { "is_dst": true, "offset": 3600 } ],
    [ "244249200", { "is_dst": false, "offset": 0 } ],
    [ "265507200", { "is_dst": true, "offset": 3600 } ],
    [ "271033200", { "is_dst": false, "offset": 0 } ],
    [ "448243200", { "is_dst": false, "offset": 3600 } ],
    [ "504918000", { "is_dst": false, "offset": 0 } ],
    [ "1212278400", { "is_dst": true, "offset": 3600 } ],
    [ "1220223600", { "is_dst": false, "offset": 0 } ],
    [ "1243814400", { "is_dst": true, "offset": 3600 } ],
    [ "1250809200", { "is_dst": false, "offset": 0 } ],
    [ "1272758400", { "is_dst": true, "offset": 3600 } ],
    [ "1281222000", { "is_dst": false, "offset": 0 } ],
    [ "1301788800", { "is_dst": true, "offset": 3600 } ],
    [ "1312066800", { "is_dst": false, "offset": 0 } ],
    [ "1335664800", { "is_dst": true, "offset": 3600 } ],
    [ "1342749600", { "is_dst": false, "offset": 0 } ],
    [ "1345428000", { "is_dst": true, "offset": 3600 } ],
    [ "1348970400", { "is_dst": false, "offset": 0 } ],
    [ "1367114400", { "is_dst": true, "offset": 3600 } ],
    [ "1373162400", { "is_dst": false, "offset": 0 } ],
    [ "1376100000", { "is_dst": true, "offset": 3600 } ],
    [ "1382839200", { "is_dst": false, "offset": 0 } ],
    [ "1396144800", { "is_dst": true, "offset": 3600 } ],
    [ "1403920800", { "is_dst": false, "offset": 0 } ],
    [ "1406944800", { "is_dst": true, "offset": 3600 } ],
    [ "1414288800", { "is_dst": false, "offset": 0 } ],
    [ "1427594400", { "is_dst": true, "offset": 3600 } ],
    [ "1434247200", { "is_dst": false, "offset": 0 } ],
    [ "1437271200", { "is_dst": true, "offset": 3600 } ],
    [ "1445738400", { "is_dst": false, "offset": 0 } ],
    [ "1459044000", { "is_dst": true, "offset": 3600 } ],
    [ "1465092000", { "is_dst": false, "offset": 0 } ],
    [ "1468116000", { "is_dst": true, "offset": 3600 } ],
    [ "1477792800", { "is_dst": false, "offset": 0 } ],
    [ "1490493600", { "is_dst": true, "offset": 3600 } ],
    [ "1495332000", { "is_dst": false, "offset": 0 } ],
    [ "1498960800", { "is_dst": true, "offset": 3600 } ],
    [ "1509242400", { "is_dst": false, "offset": 0 } ],
    [ "1521943200", { "is_dst": true, "offset": 3600 } ],
    [ "1526176800", { "is_dst": false, "offset": 0 } ],
    [ "1529200800", { "is_dst": true, "offset": 3600 } ],
    [ "1540692000", { "is_dst": false, "offset": 3600 } ],
    [ "1557021600", { "is_dst": true, "offset": 0 } ],
    [ "1560045600", { "is_dst": false, "offset": 3600 } ],
    [ "1587261600", { "is_dst": true, "offset": 0 } ],
    [ "1590890400", { "is_dst": false, "offset": 3600 } ],
    [ "1618106400", { "is_dst": true, "offset": 0 } ],
    [ "1621130400", { "is_dst": false, "offset": 3600 } ],
    [ "1648346400", { "is_dst": true, "offset": 0 } ],
    [ "1651975200", { "is_dst": false, "offset": 3600 } ],
    [ "1679191200", { "is_dst": true, "offset": 0 } ],
    [ "1682820000", { "is_dst": false, "offset": 3600 } ],
    [ "1710036000", { "is_dst": true, "offset": 0 } ],
    [ "1713060000", { "is_dst": false, "offset": 3600 } ],
    [ "1740276000", { "is_dst": true, "offset": 0 } ],
    [ "1743904800", { "is_dst": false, "offset": 3600 } ],
    [ "1771120800", { "is_dst": true, "offset": 0 } ],
    [ "1774144800", { "is_dst": false, "offset": 3600 } ],
    [ "1801965600", { "is_dst": true, "offset": 0 } ],
    [ "1804989600", { "is_dst": false, "offset": 3600 } ],
    [ "1832205600", { "is_dst": true, "offset": 0 } ],
    [ "1835834400", { "is_dst": false, "offset": 3600 } ],
    [ "1863050400", { "is_dst": true, "offset": 0 } ],
    [ "1866074400", { "is_dst": false, "offset": 3600 } ],
    [ "1893290400", { "is_dst": true, "offset": 0 } ],
    [ "1896919200", { "is_dst": false, "offset": 3600 } ],
    [ "1924135200", { "is_dst": true, "offset": 0 } ],
    [ "1927764000", { "is_dst": false, "offset": 3600 } ],
    [ "1954980000", { "is_dst": true, "offset": 0 } ],
    [ "1958004000", { "is_dst": false, "offset": 3600 } ],
    [ "1985220000", { "is_dst": true, "offset": 0 } ],
    [ "1988848800", { "is_dst": false, "offset": 3600 } ],
    [ "2016064800", { "is_dst": true, "offset": 0 } ],
    [ "2019088800", { "is_dst": false, "offset": 3600 } ],
    [ "2046304800", { "is_dst": true, "offset": 0 } ],
    [ "2049933600", { "is_dst": false, "offset": 3600 } ],
    [ "2077149600", { "is_dst": true, "offset": 0 } ],
    [ "2080778400", { "is_dst": false, "offset": 3600 } ],
    [ "2107994400", { "is_dst": true, "offset": 0 } ],
    [ "2111018400", { "is_dst": false, "offset": 3600 } ],
    [ "2138234400", { "is_dst": true, "offset": 0 } ],
    [ "2141863200", { "is_dst": false, "offset": 3600 } ],
    [ "2169079200", { "is_dst": true, "offset": 0 } ],
    [ "2172708000", { "is_dst": false, "offset": 3600 } ],
    [ "2199924000", { "is_dst": true, "offset": 0 } ],
    [ "2202948000", { "is_dst": false, "offset": 3600 } ],
    [ "2230164000", { "is_dst": true, "offset": 0 } ],
    [ "2233792800", { "is_dst": false, "offset": 3600 } ],
    [ "2261008800", { "is_dst": true, "offset": 0 } ],
    [ "2264032800", { "is_dst": false, "offset": 3600 } ],
    [ "2291248800", { "is_dst": true, "offset": 0 } ],
    [ "2294877600", { "is_dst": false, "offset": 3600 } ],
    [ "2322093600", { "is_dst": true, "offset": 0 } ],
    [ "2325722400", { "is_dst": false, "offset": 3600 } ],
    [ "2352938400", { "is_dst": true, "offset": 0 } ],
    [ "2355962400", { "is_dst": false, "offset": 3600 } ],
    [ "2383178400", { "is_dst": true, "offset": 0 } ],
    [ "2386807200", { "is_dst": false, "offset": 3600 } ],
    [ "2414023200", { "is_dst": true, "offset": 0 } ],
    [ "2417652000", { "is_dst": false, "offset": 3600 } ],
    [ "2444868000", { "is_dst": true, "offset": 0 } ],
    [ "2447892000", { "is_dst": false, "offset": 3600 } ],
    [ "2475108000", { "is_dst": true, "offset": 0 } ],
    [ "2478736800", { "is_dst": false, "offset": 3600 } ],
    [ "2505952800", { "is_dst": true, "offset": 0 } ],
    [ "2508976800", { "is_dst": false, "offset": 3600 } ],
    [ "2536192800", { "is_dst": true, "offset": 0 } ],
    [ "2539821600", { "is_dst": false, "offset": 3600 } ],
    [ "2567037600", { "is_dst": true, "offset": 0 } ],
    [ "2570666400", { "is_dst": false, "offset": 3600 } ],
    [ "2597882400", { "is_dst": true, "offset": 0 } ],
    [ "2600906400", { "is_dst": false, "offset": 3600 } ],
    [ "2628122400", { "is_dst": true, "offset": 0 } ],
    [ "2631751200", { "is_dst": false, "offset": 3600 } ],
    [ "2658967200", { "is_dst": true, "offset": 0 } ],
    [ "2662596000", { "is_dst": false, "offset": 3600 } ],
    [ "2689812000", { "is_dst": true, "offset": 0 } ],
    [ "2692836000", { "is_dst": false, "offset": 3600 } ],
    [ "2720052000", { "is_dst": true, "offset": 0 } ],
    [ "2723680800", { "is_dst": false, "offset": 3600 } ],
    [ "2750896800", { "is_dst": true, "offset": 0 } ],
    [ "2753920800", { "is_dst": false, "offset": 3600 } ],
    [ "2781136800", { "is_dst": true, "offset": 0 } ],
    [ "2784765600", { "is_dst": false, "offset": 3600 } ],
    [ "2811981600", { "is_dst": true, "offset": 0 } ],
    [ "2815610400", { "is_dst": false, "offset": 3600 } ],
    [ "2842826400", { "is_dst": true, "offset": 0 } ],
    [ "2845850400", { "is_dst": false, "offset": 3600 } ],
    [ "2873066400", { "is_dst": true, "offset": 0 } ],
    [ "2876695200", { "is_dst": false, "offset": 3600 } ],
    [ "2903911200", { "is_dst": true, "offset": 0 } ],
    [ "2907540000", { "is_dst": false, "offset": 3600 } ],
    [ "2934756000", { "is_dst": true, "offset": 0 } ],
    [ "2937780000", { "is_dst": false, "offset": 3600 } ],
    [ "2964996000", { "is_dst": true, "offset": 0 } ],
    [ "2968624800", { "is_dst": false, "offset": 3600 } ],
    [ "2995840800", { "is_dst": true, "offset": 0 } ],
    [ "2998864800", { "is_dst": false, "offset": 3600 } ],
    [ "3026080800", { "is_dst": true, "offset": 0 } ],
    [ "3029709600", { "is_dst": false, "offset": 3600 } ],
    [ "3056925600", { "is_dst": true, "offset": 0 } ],
    [ "3060554400", { "is_dst": false, "offset": 3600 } ],
    [ "3087770400", { "is_dst": true, "offset": 0 } ],
    [ "3090794400", { "is_dst": false, "offset": 3600 } ],
    [ "3118010400", { "is_dst": true, "offset": 0 } ],
    [ "3121639200", { "is_dst": false, "offset": 3600 } ],
    [ "3148855200", { "is_dst": true, "offset": 0 } ],
    [ "3152484000", { "is_dst": false, "offset": 3600 } ],
    [ "3179700000", { "is_dst": true, "offset": 0 } ],
    [ "3182724000", { "is_dst": false, "offset": 3600 } ],
    [ "3209940000", { "is_dst": true, "offset": 0 } ],
    [ "3213568800", { "is_dst": false, "offset": 3600 } ],
    [ "3240784800", { "is_dst": true, "offset": 0 } ],
    [ "3243808800", { "is_dst": false, "offset": 3600 } ],
    [ "3271024800", { "is_dst": true, "offset": 0 } ],
    [ "3274653600", { "is_dst": false, "offset": 3600 } ],
    [ "3301869600", { "is_dst": true, "offset": 0 } ],
    [ "3305498400", { "is_dst": false, "offset": 3600 } ],
    [ "3332714400", { "is_dst": true, "offset": 0 } ],
    [ "3335738400", { "is_dst": false, "offset": 3600 } ],
    [ "3362954400", { "is_dst": true, "offset": 0 } ],
    [ "3366583200", { "is_dst": false, "offset": 3600 } ],
    [ "3393799200", { "is_dst": true, "offset": 0 } ],
    [ "3397428000", { "is_dst": false, "offset": 3600 } ],
    [ "3424644000", { "is_dst": true, "offset": 0 } ],
    [ "3427668000", { "is_dst": false, "offset": 3600 } ],
    [ "3454884000", { "is_dst": true, "offset": 0 } ],
    [ "3458512800", { "is_dst": false, "offset": 3600 } ],
    [ "3485728800", { "is_dst": true, "offset": 0 } ],
    [ "3488752800", { "is_dst": false, "offset": 3600 } ],
    [ "3515968800", { "is_dst": true, "offset": 0 } ],
    [ "3519597600", { "is_dst": false, "offset": 3600 } ],
    [ "3546813600", { "is_dst": true, "offset": 0 } ],
    [ "3550442400", { "is_dst": false, "offset": 3600 } ],
    [ "3577658400", { "is_dst": true, "offset": 0 } ],
    [ "3580682400", { "is_dst": false, "offset": 3600 } ],
    [ "3607898400", { "is_dst": true, "offset": 0 } ],
    [ "3611527200", { "is_dst": false, "offset": 3600 } ],
    [ "3638743200", { "is_dst": true, "offset": 0 } ],
    [ "3642372000", { "is_dst": false, "offset": 3600 } ],
    [ "3669588000", { "is_dst": true, "offset": 0 } ],
    [ "3672612000", { "is_dst": false, "offset": 3600 } ],
    [ "3699828000", { "is_dst": true, "offset": 0 } ],
    [ "3703456800", { "is_dst": false, "offset": 3600 } ]
  ]
}