{
  "name": "Europe/Guernsey",
  "table": [
    [ "-62167168800", { "is_dst": false, "offset": 0 } ],
    [ "57722400", { "is_dst": false, "offset": 0 } ],
    [ "69818400", { "is_dst": true, "offset": 3600 } ],
    [ "89172000", { "is_dst": false, "offset": 0 } ],
    [ "101268000", { "is_dst": true, "offset": 3600 } ],
    [ "120621600", { "is_dst": false, "offset": 0 } ],
    [ "132717600", { "is_dst": true, "offset": 3600 } ],
    [ "152071200", { "is_dst": false, "offset": 0 } ],
    [ "164167200", { "is_dst": true, "offset": 3600 } ],
    [ "183520800", { "is_dst": false, "offset": 0 } ],
    [ "196221600", { "is_dst": true, "offset": 3600 } ],
    [ "214970400", { "is_dst": false, "offset": 0 } ],
    [ "227671200", { "is_dst": true, "offset": 3600 } ],
    [ "246420000", { "is_dst": false, "offset": 0 } ],
    [ "259120800", { "is_dst": true, "offset": 3600 } ],
    [ "278474400", { "is_dst": false, "offset": 0 } ],
    [ "290570400", { "is_dst": true, "offset": 3600 } ],
    [ "309924000", { "is_dst": false, "offset": 0 } ],
    [ "322020000", { "is_dst": true, "offset": 3600 } ],
    [ "341373600", { "is_dst": false, "offset": 0 } ],
    [ "354675600", { "is_dst": true, "offset": 3600 } ],
    [ "372819600", { "is_dst": false, "offset": 0 } ],
    [ "386125200", { "is_dst": true, "offset": 3600 } ],
    [ "404269200", { "is_dst": false, "offset": 0 } ],
    [ "417574800", { "is_dst": true, "offset": 3600 } ],
    [ "435718800", { "is_dst": false, "offset": 0 } ],
    [ "449024400", { "is_dst": true, "offset": 3600 } ],
    [ "467773200", { "is_dst": false, "offset": 0 } ],
    [ "481078800", { "is_dst": true, "offset": 3600 } ],
    [ "499222800", { "is_dst": false, "offset": 0 } ],
    [ "512528400", { "is_dst": true, "offset": 3600 } ],
    [ "530672400", { "is_dst": false, "offset": 0 } ],
    [ "543978000", { "is_dst": true, "offset": 3600 } ],
    [ "562122000", { "is_dst": false, "offset": 0 } ],
    [ "575427600", { "is_dst": true, "offset": 3600 } ],
    [ "593571600", { "is_dst": false, "offset": 0 } ],
    [ "606877200", { "is_dst": true, "offset": 3600 } ],
    [ "625626000", { "is_dst": false, "offset": 0 } ],
    [ "638326800", { "is_dst": true, "offset": 3600 } ],
    [ "657075600", { "is_dst": false, "offset": 0 } ],
    [ "670381200", { "is_dst": true, "offset": 3600 } ],
    [ "688525200", { "is_dst": false, "offset": 0 } ],
    [ "701830800", { "is_dst": true, "offset": 3600 } ],
    [ "719974800", { "is_dst": false, "offset": 0 } ],
    [ "733280400", { "is_dst": true, "offset": 3600 } ],
    [ "751424400", { "is_dst": false, "offset": 0 } ],
    [ "764730000", { "is_dst": true, "offset": 3600 } ],
    [ "782874000", { "is_dst": false, "offset": 0 } ],
    [ "796179600", { "is_dst": true, "offset": 3600 } ],
    [ "814323600", { "is_dst": false, "offset": 0 } ],
    [ "828234000", { "is_dst": true, "offset": 3600 } ],
    [ "846378000", { "is_dst": false, "offset": 0 } ],
    [ "859683600", { "is_dst": true, "offset": 3600 } ],
    [ "877827600", { "is_dst": false, "offset": 0 } ],
    [ "891133200", { "is_dst": true, "offset": 3600 } ],
    [ "909277200", { "is_dst": false, "offset": 0 } ],
    [ "922582800", { "is_dst": true, "offset": 3600 } ],
    [ "941331600", { "is_dst": false, "offset": 0 } ],
    [ "954032400", { "is_dst": true, "offset": 3600 } ],
    [ "972781200", { "is_dst": false, "offset": 0 } ],
    [ "985482000", { "is_dst": true, "offset": 3600 } ],
    [ "1004230800", { "is_dst": false, "offset": 0 } ],
    [ "1017536400", { "is_dst": true, "offset": 3600 } ],
    [ "1035680400", { "is_dst": false, "offset": 0 } ],
    [ "1048986000", { "is_dst": true, "offset": 3600 } ],
    [ "1067130000", { "is_dst": false, "offset": 0 } ],
    [ "1080435600", { "is_dst": true, "offset": 3600 } ],
    [ "1099184400", { "is_dst": false, "offset": 0 } ],
    [ "1111885200", { "is_dst": true, "offset": 3600 } ],
    [ "1130634000", { "is_dst": false, "offset": 0 } ],
    [ "1143334800", { "is_dst": true, "offset": 3600 } ],
    [ "1162083600", { "is_dst": false, "offset": 0 } ],
    [ "1174784400", { "is_dst": true, "offset": 3600 } ],
    [ "1193533200", { "is_dst": false, "offset": 0 } ],
    [ "1206838800", { "is_dst": true, "offset": 3600 } ],
    [ "1224982800", { "is_dst": false, "offset": 0 } ],
    [ "1238288400", { "is_dst": true, "offset": 3600 } ],
    [ "1256432400", { "is_dst": false, "offset": 0 } ],
    [ "1269738000", { "is_dst": true, "offset": 3600 } ],
    [ "1288486800", { "is_dst": false, "offset": 0 } ],
    [ "1301187600", { "is_dst": true, "offset": 3600 } ],
    [ "1319936400", { "is_dst": false, "offset": 0 } ],
    [ "1332637200", { "is_dst": true, "offset": 3600 } ],
    [ "1351386000", { "is_dst": false, "offset": 0 } ],
    [ "1364691600", { "is_dst": true, "offset": 3600 } ],
    [ "1382835600", { "is_dst": false, "offset": 0 } ],
    [ "1396141200", { "is_dst": true, "offset": 3600 } ],
    [ "1414285200", { "is_dst": false, "offset": 0 } ],
    [ "1427590800", { "is_dst": true, "offset": 3600 } ],
    [ "1445734800", { "is_dst": false, "offset": 0 } ],
    [ "1459040400", { "is_dst": true, "offset": 3600 } ],
    [ "1477789200", { "is_dst": false, "offset": 0 } ],
    [ "1490490000", { "is_dst": true, "offset": 3600 } ],
    [ "1509238800", { "is_dst": false, "offset": 0 } ],
    [ "1521939600", { "is_dst": true, "offset": 3600 } ],
    [ "1540688400", { "is_dst": false, "offset": 0 } ],
    [ "1553994000", { "is_dst": true, "offset": 3600 } ],
    [ "1572138000", { "is_dst": false, "offset": 0 } ],
    [ "1585443600", { "is_dst": true, "offset": 3600 } ],
    [ "1603587600", { "is_dst": false, "offset": 0 } ],
    [ "1616893200", { "is_dst": true, "offset": 3600 } ],
    [ "1635642000", { "is_dst": false, "offset": 0 } ],
    [ "1648342800", { "is_dst": true, "offset": 3600 } ],
    [ "1667091600", { "is_dst": false, "offset": 0 } ],
    [ "1679792400", { "is_dst": true, "offset": 3600 } ],
    [ "1698541200", { "is_dst": false, "offset": 0 } ],
    [ "1711846800", { "is_dst": true, "offset": 3600 } ],
    [ "1729990800", { "is_dst": false, "offset": 0 } ],
    [ "1743296400", { "is_dst": true, "offset": 3600 } ],
    [ "1761440400", { "is_dst": false, "offset": 0 } ],
    [ "1774746000", { "is_dst": true, "offset": 3600 } ],
    [ "1792890000", { "is_dst": false, "offset": 0 } ],
    [ "1806195600", { "is_dst": true, "offset": 3600 } ],
    [ "1824944400", { "is_dst": false, "offset": 0 } ],
    [ "1837645200", { "is_dst": true, "offset": 3600 } ],
    [ "1856394000", { "is_dst": false, "offset": 0 } ],
    [ "1869094800", { "is_dst": true, "offset": 3600 } ],
    [ "1887843600", { "is_dst": false, "offset": 0 } ],
    [ "1901149200", { "is_dst": true, "offset": 3600 } ],
    [ "1919293200", { "is_dst": false, "offset": 0 } ],
    [ "1932598800", { "is_dst": true, "offset": 3600 } ],
    [ "1950742800", { "is_dst": false, "offset": 0 } ],
    [ "1964048400", { "is_dst": true, "offset": 3600 } ],
    [ "1982797200", { "is_dst": false, "offset": 0 } ],
    [ "1995498000", { "is_dst": true, "offset": 3600 } ],
    [ "2014246800", { "is_dst": false, "offset": 0 } ],
    [ "2026947600", { "is_dst": true, "offset": 3600 } ],
    [ "2045696400", { "is_dst": false, "offset": 0 } ],
    [ "2058397200", { "is_dst": true, "offset": 3600 } ],
    [ "2077146000", { "is_dst": false, "offset": 0 } ],
    [ "2090451600", { "is_dst": true, "offset": 3600 } ],
    [ "2108595600", { "is_dst": false, "offset": 0 } ],
    [ "2121901200", { "is_dst": true, "offset": 3600 } ],
    [ "2140045200", { "is_dst": false, "offset": 0 } ],
    [ "2153350800", { "is_dst": true, "offset": 3600 } ],
    [ "2172099600", { "is_dst": false, "offset": 0 } ],
    [ "2184800400", { "is_dst": true, "offset": 3600 } ],
    [ "2203549200", { "is_dst": false, "offset": 0 } ]
  ]
}