{
  "name": "Europe/Moscow",
  "table": [
    [ "-62167168800", { "is_dst": false, "offset": 9017 } ],
    [ "-2840149817", { "is_dst": false, "offset": 9017 } ],
    [ "-1688265017", { "is_dst": false, "offset": 9079 } ],
    [ "-1656819079", { "is_dst": true, "offset": 12679 } ],
    [ "-1641353479", { "is_dst": false, "offset": 9079 } ],
    [ "-1627965079", { "is_dst": true, "offset": 16279 } ],
    [ "-1618716679", { "is_dst": true, "offset": 12679 } ],
    [ "-1596429079", { "is_dst": true, "offset": 16279 } ],
    [ "-1593820800", { "is_dst": true, "offset": 14400 } ],
    [ "-1589860800", { "is_dst": false, "offset": 10800 } ],
    [ "-1542427200", { "is_dst": true, "offset": 14400 } ],
    [ "-1539493200", { "is_dst": true, "offset": 18000 } ],
    [ "-1525323600", { "is_dst": true, "offset": 14400 } ],
    [ "-1522728000", { "is_dst": false, "offset": 10800 } ],
    [ "-1491188400", { "is_dst": false, "offset": 7200 } ],
    [ "-1247536800", { "is_dst": false, "offset": 10800 } ],
    [ "354920400", { "is_dst": true, "offset": 14400 } ],
    [ "370728000", { "is_dst": false, "offset": 10800 } ],
    [ "386456400", { "is_dst": true, "offset": 14400 } ],
    [ "402264000", { "is_dst": false, "offset": 10800 } ],
    [ "417992400", { "is_dst": true, "offset": 14400 } ],
    [ "433800000", { "is_dst": false, "offset": 10800 } ],
    [ "449614800", { "is_dst": true, "offset": 14400 } ],
    [ "465346800", { "is_dst": false, "offset": 10800 } ],
    [ "481071600", { "is_dst": true, "offset": 14400 } ],
    [ "496796400", { "is_dst": false, "offset": 10800 } ],
    [ "512521200", { "is_dst": true, "offset": 14400 } ],
    [ "528246000", { "is_dst": false, "offset": 10800 } ],
    [ "543970800", { "is_dst": true, "offset": 14400 } ],
    [ "559695600", { "is_dst": false, "offset": 10800 } ],
    [ "575420400", { "is_dst": true, "offset": 14400 } ],
    [ "591145200", { "is_dst": false, "offset": 10800 } ],
    [ "606870000", { "is_dst": true, "offset": 14400 } ],
    [ "622594800", { "is_dst": false, "offset": 10800 } ],
    [ "638319600", { "is_dst": true, "offset": 14400 } ],
    [ "654649200", { "is_dst": false, "offset": 10800 } ],
    [ "670374000", { "is_dst": true, "offset": 10800 } ],
    [ "686102400", { "is_dst": false, "offset": 7200 } ],
    [ "695779200", { "is_dst": false, "offset": 10800 } ],
    [ "701823600", { "is_dst": true, "offset": 14400 } ],
    [ "717548400", { "is_dst": false, "offset": 10800 } ],
    [ "733273200", { "is_dst": true, "offset": 14400 } ],
    [ "748998000", { "is_dst": false, "offset": 10800 } ],
    [ "764722800", { "is_dst": true, "offset": 14400 } ],
    [ "780447600", { "is_dst": false, "offset": 10800 } ],
    [ "796172400", { "is_dst": true, "offset": 14400 } ],
    [ "811897200", { "is_dst": false, "offset": 10800 } ],
    [ "828226800", { "is_dst": true, "offset": 14400 } ],
    [ "846370800", { "is_dst": false, "offset": 10800 } ],
    [ "859676400", { "is_dst": true, "offset": 14400 } ],
    [ "877820400", { "is_dst": false, "offset": 10800 } ],
    [ "891126000", { "is_dst": true, "offset": 14400 } ],
    [ "909270000", { "is_dst": false, "offset": 10800 } ],
    [ "922575600", { "is_dst": true, "offset": 14400 } ],
    [ "941324400", { "is_dst": false, "offset": 10800 } ],
    [ "954025200", { "is_dst": true, "offset": 14400 } ],
    [ "972774000", { "is_dst": false, "offset": 10800 } ],
    [ "985474800", { "is_dst": true, "offset": 14400 } ],
    [ "1004223600", { "is_dst": false, "offset": 10800 } ],
    [ "1017529200", { "is_dst": true, "offset": 14400 } ],
    [ "1035673200", { "is_dst": false, "offset": 10800 } ],
    [ "1048978800", { "is_dst": true, "offset": 14400 } ],
    [ "1067122800", { "is_dst": false, "offset": 10800 } ],
    [ "1080428400", { "is_dst": true, "offset": 14400 } ],
    [ "1099177200", { "is_dst": false, "offset": 10800 } ],
    [ "1111878000", { "is_dst": true, "offset": 14400 } ],
    [ "1130626800", { "is_dst": false, "offset": 10800 } ],
    [ "1143327600", { "is_dst": true, "offset": 14400 } ],
    [ "1162076400", { "is_dst": false, "offset": 10800 } ],
    [ "1174777200", { "is_dst": true, "offset": 14400 } ],
    [ "1193526000", { "is_dst": false, "offset": 10800 } ],
    [ "1206831600", { "is_dst": true, "offset": 14400 } ],
    [ "1224975600", { "is_dst": false, "offset": 10800 } ],
    [ "1238281200", { "is_dst": true, "offset": 14400 } ],
    [ "1256425200", { "is_dst": false, "offset": 10800 } ],
    [ "1269730800", { "is_dst": true, "offset": 14400 } ],
    [ "1288479600", { "is_dst": false, "offset": 10800 } ],
    [ "1301180400", { "is_dst": false, "offset": 14400 } ],
    [ "1414274400", { "is_dst": false, "offset": 10800 } ]
  ]
}